igneous/__init__.py
igneous/client.py
igneous/request.py
igneous/response.py
igneous/test_utils.py
igneous/util.py
igneous-1.1.1.dist-info/LICENSE
igneous-1.1.1.dist-info/METADATA
igneous-1.1.1.dist-info/WHEEL
igneous-1.1.1.dist-info/top_level.txt
igneous-1.1.1.dist-info/RECORD
