Metadata-Version: 2.1
Name: igneous
Version: 1.1.1
Summary: Igneous API Python SDK
Home-page: https://github.com/igneous-systems/python-igneous
Author: Gui Rava
Author-email: guirava@igneous.io
License: UNKNOWN
Platform: UNKNOWN
Classifier: Programming Language :: Python :: 3
Classifier: License :: OSI Approved :: Apache Software License
Classifier: Operating System :: OS Independent
Requires-Python: >=3.6
